loomxpy/__init__.py
loomxpy/_errors.py
loomxpy/_hooks.py
loomxpy/_loomx.py
loomxpy/_matrix.py
loomxpy/_mode.py
loomxpy/_s7.py
loomxpy/cli.py
loomxpy/loomxpy.py
loomxpy/utils.py
loomxpy/_specifications/__init__.py
tests/__init__.py
tests/test_loomxpy.py
loomxpy-0.4.2.dist-info/AUTHORS.rst
loomxpy-0.4.2.dist-info/LICENSE
loomxpy-0.4.2.dist-info/METADATA
loomxpy-0.4.2.dist-info/WHEEL
loomxpy-0.4.2.dist-info/top_level.txt
loomxpy-0.4.2.dist-info/RECORD
