Metadata-Version: 2.1
Name: loomxpy
Version: 0.4.2
Summary: Python package to create .loom files (compatible with SCope) and extend them with other data (e.g.: SCENIC regulons)
Home-page: https://github.com/aertslab/LoomXpy
Author: Maxime De Waegeneer, Kristofer Davie
License: MIT
Keywords: SCope,loom,single-cell
Platform: any
License-File: LICENSE
License-File: AUTHORS.rst
Requires-Dist: loompy (==3.0.7)
Requires-Dist: networkx
Requires-Dist: numpy
Requires-Dist: pandas
Requires-Dist: pyscenic (>=0.12.0)
Requires-Dist: scikit-learn (>=0.22.2)
Requires-Dist: ctxcore (>=0.2.0)
